keyboard_shortcuts
example
