Metadata-Version: 1.0
Name: django-keyboard-shortcuts
Version: 0.0.7
Summary: Helps to use the keyboard inside your web project.
Home-page: https://bitbucket.org/DNX/django-keyboard-shorcuts/
Author: Denis Darii
Author-email: denis.darii@gmail.com
License: BSD License
Platform: UNKNOWN
Classifier: Development Status :: 3 - Alpha
Classifier: Intended Audience :: Developers
Classifier: Operating System :: OS Independent
Classifier: License :: OSI Approved :: BSD License
Classifier: Programming Language :: Python
Classifier: Topic :: Software Development
Classifier: Topic :: Software Development :: Libraries :: Python Modules
